setup.py
SerializerOfJsonAndXml.egg-info/PKG-INFO
SerializerOfJsonAndXml.egg-info/SOURCES.txt
SerializerOfJsonAndXml.egg-info/dependency_links.txt
SerializerOfJsonAndXml.egg-info/requires.txt
SerializerOfJsonAndXml.egg-info/top_level.txt
serializers/__init__.py
serializers/factory.py